kucoin_futures/__init__.py
kucoin_futures/client.py
kucoin_futures/ws_client.py
kucoin_futures/base_request/__init__.py
kucoin_futures/base_request/base_request.py
kucoin_futures/marke_data/__init__.py
kucoin_futures/marke_data/market_data.py
kucoin_futures/trade/__init__.py
kucoin_futures/trade/trade.py
kucoin_futures/user/__init__.py
kucoin_futures/user/user.py
kucoin_futures/websocket/__init__.py
kucoin_futures/websocket/websocket.py
kucoin_futures/ws_token/__init__.py
kucoin_futures/ws_token/token.py
kucoin_futures_python-1.0.14.dist-info/LICENSE
kucoin_futures_python-1.0.14.dist-info/METADATA
kucoin_futures_python-1.0.14.dist-info/WHEEL
kucoin_futures_python-1.0.14.dist-info/top_level.txt
kucoin_futures_python-1.0.14.dist-info/RECORD
